LICENSE
MANIFEST.in
README.rst
setup.py
docs/Makefile
docs/about.rst
docs/conf.py
docs/index.rst
docs/installation.rst
docs/releasenotes.rst
docs/usage.rst
requirements/base.txt
requirements/production.txt
requirements/test.txt
zinnia_drupal/__init__.py
zinnia_drupal.egg-info/PKG-INFO
zinnia_drupal.egg-info/SOURCES.txt
zinnia_drupal.egg-info/dependency_links.txt
zinnia_drupal.egg-info/requires.txt
zinnia_drupal.egg-info/top_level.txt
zinnia_drupal/management/__init__.py
zinnia_drupal/management/commands/__init__.py
zinnia_drupal/management/commands/drupal62zinnia.py