Metadata-Version: 1.1
Name: zinnia-drupal
Version: 0.1.2
Summary: Helper application for importing content from Drupal database into Zinnia.
Home-page: https://github.com/azaghal/zinnia-drupal
Author: Branko Majic
Author-email: branko@majic.rs
License: BSD
Platform: UNKNOWN
Classifier: Environment :: Web Environment
Classifier: Framework :: Django
Classifier: Intended Audience :: Developers
Classifier: License :: OSI Approved :: BSD License
Classifier: Operating System :: OS Independent
Classifier: Programming Language :: Python
Classifier: Programming Language :: Python :: 2.7
Classifier: Topic :: Internet :: WWW/HTTP
Classifier: Topic :: Internet :: WWW/HTTP :: Dynamic Content
